<?xml version='1.0' encoding='UTF-8'?>
<!DOCTYPE hibernate-configuration PUBLIC
          "-//Hibernate/Hibernate Configuration DTD 3.0//EN"
          "http://hibernate.sourceforge.net/hibernate-configuration-3.0.dtd">

<!-- Generated by MyEclipse Hibernate Tools.                   -->
<hibernate-configuration>

	<session-factory>
		<property name="myeclipse.connection.profile">MySQL</property>
		<property name="connection.url">
			jdbc:mysql://localhost:3306/SpringMVC-ElectronicEmporium
		</property>
		<property name="connection.username">root</property>
		<property name="connection.password">110202021030cjx?</property>
		<property name="connection.driver_class">
			com.mysql.jdbc.Driver
		</property>
		<property name="dialect">
			org.hibernate.dialect.MySQLDialect
		</property>
		<property name="javax.persistence.validation.mode">
			none
		</property>
		<property name="hibernate.show_sql">true</property>
		<mapping resource="com/legou/entities/User.hbm.xml" />
		<mapping resource="com/legou/models/TableCustomer.hbm.xml" />
		<mapping resource="com/legou/models/TableClerk.hbm.xml" />
		<mapping resource="com/legou/models/TableOrder.hbm.xml" />
		<mapping resource="com/legou/models/OrderGoods.hbm.xml" />
		<mapping resource="com/legou/models/Goods.hbm.xml" />
		<mapping resource="com/legou/models/Administrator.hbm.xml" />
		<mapping resource="com/legou/models/Orders.hbm.xml" />
		<mapping resource="com/legou/models/AttrValue.hbm.xml" />
		<mapping resource="com/legou/models/Addgoods.hbm.xml" />
		<mapping resource="com/legou/models/Goodstype.hbm.xml" />
		<mapping resource="com/legou/models/Reciever.hbm.xml" />
		<mapping resource="com/legou/models/Clerk.hbm.xml" />
		<mapping resource="com/legou/models/Shoppingcart.hbm.xml" />
		<mapping resource="com/legou/models/GoodstAttr.hbm.xml" />
		<mapping resource="com/legou/models/Customer.hbm.xml" />

	</session-factory>

</hibernate-configuration>